joblib_windower/__init__.py
joblib_windower/errors.py
joblib_windower/slide_ndarrays.py
joblib_windower/slide_ndframes.py
joblib_windower-0.6.2.dist-info/METADATA
joblib_windower-0.6.2.dist-info/WHEEL
joblib_windower-0.6.2.dist-info/top_level.txt
joblib_windower-0.6.2.dist-info/RECORD
